{
  "nestedObj": [
    {
      "name": "ravi-edit",
      "age": 27,
      "address": "cbe-2",
      "funds": {
        "mf": "reliance-2",
        "stocks": "supremevilla-2"
      },
      "id": 2
    },
    {
      "name": "maha",
      "age": 28,
      "address": "cbe",
      "funds": {
        "mf": "supremevilla",
        "stocks": "TATA"
      },
      "id": 4
    }
  ],
  "user": [
    {
      "FirstName": "durai",
      "LastName": "nattu",
      "PhoneNumber": "8001188800",
      "email": "mahaee@gamil.com",
      "id": 6
    },
    {
      "FirstName": "akashaaa",
      "LastName": "akas",
      "PhoneNumber": "8899988777",
      "email": "aka@gmail.com",
      "id": 7
    }
  ],
  "posts": [
    {
      "id": 1,
      "title": "json-server",
      "author": "typicode"
    }
  ],
  "comments": [
    {
      "id": 1,
      "body": "some comment",
      "postId": 1
    }
  ],
  "profile": {
    "name": "typicode"
  }
}